pshitt.py
pshitt-1.0.1.dist-info/LICENSE
pshitt-1.0.1.dist-info/METADATA
pshitt-1.0.1.dist-info/WHEEL
pshitt-1.0.1.dist-info/entry_points.txt
pshitt-1.0.1.dist-info/top_level.txt
pshitt-1.0.1.dist-info/RECORD
