Metadata-Version: 2.1
Name: pshitt
Version: 1.0.1
Summary: Passwords of SSH Intruders Transferred to Text
Home-page: https://github.com/regit/pshitt
Author: Eric Leblond
License: UNKNOWN
Project-URL: Bug Reports, https://github.com/regit/pshitt/issues
Project-URL: Source, https://github.com/regit/pshitt/
Keywords: ssh intrusion-detection
Platform: UNKNOWN
Classifier: Development Status :: 5 - Production/Stable
Classifier: Intended Audience :: Information Technology
Classifier: Topic :: Security
Classifier: License :: OSI Approved :: GNU General Public License v3 (GPLv3)
Classifier: Programming Language :: Python :: 2
Classifier: Programming Language :: Python :: 2.7
Classifier: Programming Language :: Python :: 3
Classifier: Programming Language :: Python :: 3.5
Classifier: Programming Language :: Python :: 3.6
Classifier: Programming Language :: Python :: 3.7
Classifier: Programming Language :: Python :: 3.8
Requires-Python: >=2.7, !=3.0.*, !=3.1.*, !=3.2.*, !=3.3.*, !=3.4.*, <4
Requires-Dist: paramiko
Requires-Dist: python-daemon
